LICENSE.rst
MANIFEST.in
README.rst
setup.py
agoraplex/__init__.py
agoraplex.themes.sphinx.egg-info/PKG-INFO
agoraplex.themes.sphinx.egg-info/SOURCES.txt
agoraplex.themes.sphinx.egg-info/dependency_links.txt
agoraplex.themes.sphinx.egg-info/namespace_packages.txt
agoraplex.themes.sphinx.egg-info/not-zip-safe
agoraplex.themes.sphinx.egg-info/requires.txt
agoraplex.themes.sphinx.egg-info/top_level.txt
agoraplex/themes/__init__.py
agoraplex/themes/sphinx/__init__.py
agoraplex/themes/sphinx/roles.py
agoraplex/themes/sphinx/support.py
agoraplex/themes/sphinx/agoraplex/layout.html
agoraplex/themes/sphinx/agoraplex/theme.conf
agoraplex/themes/sphinx/agoraplex/static/agoraplex-latex.png
agoraplex/themes/sphinx/agoraplex/static/agoraplex-small.png
agoraplex/themes/sphinx/agoraplex/static/agoraplex.css_t
agoraplex/themes/sphinx/agoraplex/static/agoraplex.ico
agoraplex/themes/sphinx/agoraplex/static/agoraplex.png
agoraplex/themes/sphinx/agoraplex/static/dialog-note.png
agoraplex/themes/sphinx/agoraplex/static/dialog-seealso.png
agoraplex/themes/sphinx/agoraplex/static/dialog-topic.png
agoraplex/themes/sphinx/agoraplex/static/dialog-warning.png
agoraplex/themes/sphinx/agoraplex/static/epub.css
agoraplex/themes/sphinx/agoraplex/static/footerbg.png
agoraplex/themes/sphinx/agoraplex/static/headerbg.png
agoraplex/themes/sphinx/agoraplex/static/ie6.css
agoraplex/themes/sphinx/agoraplex/static/in_progress.png
agoraplex/themes/sphinx/agoraplex/static/middlebg.png
agoraplex/themes/sphinx/agoraplex/static/transparent.gif
agoraplex/themes/sphinx/agoraplex/static/fonts/neuton/LICENSE.txt
agoraplex/themes/sphinx/agoraplex/static/fonts/neuton/regular.eot
agoraplex/themes/sphinx/agoraplex/static/fonts/neuton/regular.svg
agoraplex/themes/sphinx/agoraplex/static/fonts/neuton/regular.ttf
agoraplex/themes/sphinx/agoraplex/static/fonts/neuton/regular.woff
agoraplex/themes/sphinx/agoraplex/static/fonts/neuton/stylesheet.css
agoraplex/themes/sphinx/agoraplex/static/fonts/nobile/LICENSE.txt
agoraplex/themes/sphinx/agoraplex/static/fonts/nobile/bold.eot
agoraplex/themes/sphinx/agoraplex/static/fonts/nobile/bold.svg
agoraplex/themes/sphinx/agoraplex/static/fonts/nobile/bold.ttf
agoraplex/themes/sphinx/agoraplex/static/fonts/nobile/bold.woff
agoraplex/themes/sphinx/agoraplex/static/fonts/nobile/bold_italic.eot
