Metadata-Version: 1.1
Name: agoraplex.themes.sphinx
Version: 0.1.3
Summary: A Sphinx theme for Agoraplex projects, based on the Pylons Sphinx theme
Home-page: https://github.com/agoraplex/themes
Author: Tripp Lilley
Author-email: tripplilley@gmail.com
License: See LICENSE.rst
Keywords: sphinx extension theme agoraplex
Platform: UNKNOWN
Classifier: Development Status :: 4 - Beta
Classifier: Intended Audience :: Developers
Classifier: Operating System :: OS Independent
Classifier: Programming Language :: Python :: 2.7
Classifier: Topic :: Documentation
Classifier: Topic :: Software Development :: Documentation
